moomoo_mcp/__init__.py
moomoo_mcp/server.py
moomoo_mcp/resources/__init__.py
moomoo_mcp/services/__init__.py
moomoo_mcp/services/base_service.py
moomoo_mcp/services/market_data_service.py
moomoo_mcp/services/trade_service.py
moomoo_mcp/tools/__init__.py
moomoo_mcp/tools/account.py
moomoo_mcp/tools/market_data.py
moomoo_mcp/tools/system.py
moomoo_mcp/tools/trading.py
moomoo_api_mcp-0.1.7.dist-info/METADATA
moomoo_api_mcp-0.1.7.dist-info/WHEEL
moomoo_api_mcp-0.1.7.dist-info/entry_points.txt
moomoo_api_mcp-0.1.7.dist-info/licenses/LICENSE
moomoo_api_mcp-0.1.7.dist-info/RECORD
