Metadata-Version: 2.4
Name: moomoo-api-mcp
Version: 0.1.7
Summary: Moomoo API MCP Server
Project-URL: Repository, https://github.com/Litash/moomoo-api-mcp
Project-URL: Issues, https://github.com/Litash/moomoo-api-mcp/issues
Author-email: Yichen Lu <yichen.lu529@gamil.com>
License:                                  Apache License
License-File: LICENSE
Keywords: ai,finance,mcp,moomoo,trading
Classifier: Development Status :: 3 - Alpha
Classifier: Intended Audience :: Developers
Classifier: Intended Audience :: Financial and Insurance Industry
Classifier: License :: OSI Approved :: Apache Software License
Classifier: Programming Language :: Python :: 3
Classifier: Programming Language :: Python :: 3.10
Classifier: Programming Language :: Python :: 3.11
Classifier: Programming Language :: Python :: 3.12
Classifier: Programming Language :: Python :: 3.13
Classifier: Topic :: Office/Business :: Financial :: Investment
Requires-Python: >=3.10
Requires-Dist: mcp>=1.0.0
Requires-Dist: moomoo-api>=3.3.0
Requires-Dist: pandas>=2.0.0
Provides-Extra: dev
Requires-Dist: pytest-asyncio>=0.23.0; extra == 'dev'
Requires-Dist: pytest>=8.0.0; extra == 'dev'
Requires-Dist: ruff>=0.4.0; extra == 'dev'
